iwannadie/__init__.py
iwannadie/bda1.py
iwannadie/bda2.py
iwannadie/bda3.py
iwannadie/bda4.py
iwannadie/bi2.py
iwannadie/bi5.py
iwannadie/bi6.py
iwannadie/dl1.py
iwannadie/dl2.py
iwannadie/dl3.py
iwannadie/dl4.py
iwannadie/dl5.py
iwannadie-0.7.0.dist-info/METADATA
iwannadie-0.7.0.dist-info/WHEEL
iwannadie-0.7.0.dist-info/top_level.txt
iwannadie-0.7.0.dist-info/RECORD
