Metadata-Version: 2.1
Name: iwannadie
Version: 0.7.0
Summary: A God like library created by a god like person. Friends enjoy your 2 days, at my place called earth
Author: godORwhat
Author-email: iwannadie@nature.com
License: MIT
Classifier: Programming Language :: Python :: 3
Requires-Python: >=3.6
